{
  "slug": "phonak-audeo-lumity-30",
  "marque": "phonak",
  "marqueLabel": "Phonak",
  "groupe": "sonova",
  "modele": "Audéo Lumity",
  "formeType": "RIC",
  "formesDisponibles": "RIC R|RIC RT|RIC 312",
  "puce": "PRISM",
  "niveau": "30",
  "niveauRaw": "L30",
  "niveauPosition": 2,
  "classe": "2",
  "rac0": false,
  "prix": {
    "eur": {
      "min": 1100,
      "max": 1400
    }
  },
  "annee": 2022,
  "specs": {
    "canaux": 8,
    "bandes": 8,
    "batterie": "Li-ion rechargeable ou pile 312",
    "autonomie": "16-24",
    "ip": "IP68",
    "plageAdaptation": "Légère à sévère"
  },
  "connectivite": {
    "bluetooth": "Bluetooth Classic + BLE",
    "auracast": false,
    "application": "myPhonak",
    "mainLibre": true
  },
  "fonctionnalites": {
    "rechargeable": true,
    "bobineT": true,
    "acouphenes": true,
    "antiFeedback": "WhistleBlock",
    "micDirectionnels": "SmartSpeech Technology"
  },
  "couleurs": 9,
  "sourceUrl": "https://www.phonak.com/en-us/hearing-devices/hearing-aids/audeo-lumity",
  "venduEnEurope": true,
  "ficheTechniquePdf": "/docs/fiches-techniques/phonak-audeo-lumity-datasheet.pdf",
  "descriptionCourte": "RIC Phonak Lumity entrée de gamme. BT universel inclus, 8 canaux. Generation éprouvée au prix le plus accessible de la gamme Phonak actuelle.",
  "descriptionComplete": "Le Lumity 30, c’est l’entrée de gamme Phonak avec la connectivité universelle. Pour moins de 1 000€ par appareil, vous avez le Bluetooth Classic qui fonctionne avec tous les téléphones, l’app myPhonak et un appareil fiable.\n\nCe que fait cet appareil\n8 canaux et 8 bandes — c’est le minimum de la gamme Lumity. Dans le calme, les conversations sont claires et confortables. Dans le bruit, il faut être honnête : c’est limité. Le Lumity 30 est fait pour un quotidien calme.\n\nL’atout du 30 : le Bluetooth Classic est là quand même. Et la bobine T est disponible sur la version RT. C’est rare à ce prix.\n\nEn pratique, sur le terrain\nJ’ai adapté le Lumity 30 sur des patients avec un budget très serré mais qui voulaient rester chez Phonak. Pour entendre la télé, suivre une conversation à deux, passer des appels — mission accomplie. Pas de miracle en milieu bruyant, mais c’est attendu à ce niveau.\n\nPour qui est fait cet appareil ?\nPremier appareillage à budget minimum, quotidien calme, besoin du Bluetooth universel.\n\nVerdict expert\n7.5/10. Le Lumity 30 donne accès à l’écosystème Phonak au prix le plus bas. La gestion du bruit est basique mais la connectivité universelle est un vrai avantage à ce tarif.\n\nEn une phrase : le Phonak le moins cher avec le Bluetooth universel.",
  "pointsForts": [
    "Bluetooth Classic universel inclus — exceptionnel à ce prix",
    "Prix le plus accessible de la gamme Phonak actuelle : dès 900€",
    "Génération Lumity fiable, myPhonak complète",
    "Disponible en rechargeable et pile 312 + bobine T en option (RT)"
  ],
  "pointsFaibles": [
    "8 canaux — gestion du bruit très basique, réservé aux quotidiens calmes",
    "Pas de StereoZoom — pas de focalisation directionnelle en milieu bruyant",
    "Autonomie rechargeable 16-24h — la plus courte de la gamme actuelle"
  ],
  "noteExpert": 7.5,
  "enAvant": false,
  "legacy": false,
  "metaTitle": "Phonak Audéo Lumity 30 : prix, avis et fiche",
  "metaDescription": "RIC Phonak Lumity entrée de gamme. BT universel, 8 canaux. Dès 900€. Le Phonak le moins cher. Avis audioprothésiste DE.",
  "image": "/images/appareils/aide-auditive-phonak-audeo-lumity-1.webp",
  "gallery": [
    "/images/appareils/aide-auditive-phonak-audeo-lumity-1.webp",
    "/images/appareils/aide-auditive-phonak-audeo-lumity-2.webp",
    "/images/appareils/aide-auditive-phonak-audeo-lumity-3.webp",
    "/images/appareils/aide-auditive-phonak-audeo-lumity-4.webp"
  ]
}
