{
  "marque": "resound",
  "marqueLabel": "ReSound",
  "groupe": "gn",
  "modele": "Enzo IA",
  "formeType": "BTE",
  "formesDisponibles": "BTE SP",
  "annee": 2025,
  "specs": {
    "batterie": "Li-ion",
    "autonomie": "28",
    "ip": "IP68",
    "plageAdaptation": "Severe to profound"
  },
  "connectivite": {
    "bluetooth": "BLE LE Audio",
    "auracast": true,
    "mainLibre": false
  },
  "fonctionnalites": {
    "rechargeable": true,
    "bobineT": true,
    "acouphenes": false
  },
  "sourceUrl": "HearingTracker",
  "venduEnEurope": true,
  "slug": "resound-enzo-ia-9",
  "niveau": "9",
  "niveauRaw": "9",
  "niveauPosition": 4,
  "rac0": false,
  "image": "/images/appareils/aide-auditive-resound-enzo-ia-9.jpg",
  "descriptionCourte": "Le ReSound Enzo IA 9 est un appareil auditif BTE premium, lance en 2025 par ReSound (groupe GN). Rechargeable avec 28h d'autonomie. Connectivite BLE LE Audio avec Auracast.",
  "pointsForts": [
    "Puissant, robuste, adapte aux pertes severes a profondes",
    "Rechargeable (28h)",
    "Bluetooth BLE LE Audio",
    "Compatible Auracast",
    "Etanche IP68"
  ],
  "pointsFaibles": [
    "Plus visible derriere l'oreille"
  ],
  "noteExpert": 8.9,
  "enAvant": true,
  "ficheTechniquePdf": "/docs/fiches-techniques/resound-omnia-brochure.pdf",
  "descriptionComplete": "Le ReSound Enzo IA 9 est une aide auditive de type contour d'oreille classique (BTE), robuste et puissant, adapte aux pertes severes a profondes. Lance en 2025 par ReSound (groupe GN), pionnier du Made for iPhone et du Bluetooth LE Audio, cet appareil se positionne en niveau Premium, offrant le meilleur traitement du signal et les technologies les plus recentes.\n\nTechnologie et traitement du son\nle Enzo IA beneficie de la technologie M&RIE (Microphone & Receiver-In-Ear). Micro dans le conduit pour une spatialisation naturelle, Auracast. La plage d'adaptation couvre les pertes Severe a profondes. \n\nConnectivite\nLa connectivite BLE LE Audio permet le streaming audio direct depuis votre smartphone. La compatibilite Auracast ouvre l'acces aux flux audio publics (cinemas, conferences, lieux de culte). \n\nConfort et autonomie\nLe Enzo IA est rechargeable (batterie Li-ion), offrant jusqu'a 28 heures d'autonomie par charge. Un chargeur est fourni avec l'appareil. La certification IP68 garantit une resistance a l'eau et a la poussiere pour une utilisation sans souci au quotidien. \n\nFonctionnalites complementaires\nLe Enzo IA integre egalement une bobine telephonique (T-coil) pour les boucles magnetiques. \n\nPrix et remboursement\nLe prix est communique sur devis par votre audioprothesiste. Un essai gratuit de 30 jours est obligatoire avant tout achat definitif.\n\nL'avis de l'audioprothesiste\nNote expert : 8.9/10. Le ReSound Enzo IA 9 est un appareil auditif BTE premium, lance en 2025 par ReSound (groupe GN). Rechargeable avec 28h d'autonomie. Connectivite BLE LE Audio avec Auracast."
}
