{
  "slug": "signia-pure-ix-3",
  "marque": "signia",
  "marqueLabel": "Signia",
  "groupe": "ws-audiology",
  "modele": "Pure Charge&Go IX",
  "formeType": "RIC",
  "formesDisponibles": "RIC|RIC T",
  "puce": "IX Platform",
  "niveau": "3",
  "niveauRaw": "3IX",
  "niveauPosition": 2,
  "classe": "2",
  "rac0": false,
  "prix": {
    "eur": {
      "min": 995,
      "max": 1090
    }
  },
  "annee": 2023,
  "specs": {
    "canaux": 24,
    "bandes": 12,
    "batterie": "Li-ion rechargeable",
    "autonomie": "34-39",
    "ip": "IP68",
    "plageAdaptation": "L\u00e9g\u00e8re \u00e0 s\u00e9v\u00e8re",
    "poids": "2.1g"
  },
  "connectivite": {
    "bluetooth": "BLE LE Audio",
    "auracast": false,
    "application": "Signia App",
    "mainLibre": true
  },
  "fonctionnalites": {
    "rechargeable": true,
    "bobineT": false,
    "acouphenes": true,
    "antiFeedback": "Feedback Canceller IX",
    "micDirectionnels": "OVP 2.0 + Split Processing"
  },
  "couleurs": 10,
  "image": "/images/appareils/aide-auditive-signia-pure-ix-3.jpg",
  "sourceUrl": "https://www.signia.net/en-us/hearing-aids/integrated-xperience/pure-charge-go-ix/",
  "venduEnEurope": true,
  "ficheTechniquePdf": "/docs/fiches-techniques/signia-pure-chargeandgo-ix-fiche.pdf",
  "descriptionCourte": "RIC Signia d\u2019entr\u00e9e de gamme IX, m\u00eame puce que le niveau 7 \u00e0 prix accessible. OVP 2.0, 39h d\u2019autonomie. Pour les pertes l\u00e9g\u00e8res \u00e0 mod\u00e9r\u00e9es cherchant un premier appareillage Signia fiable.",
  "descriptionComplete": "La question que beaucoup de patients me posaient quand Signia a lanc\u00e9 la gamme IX : \u00ab Est-ce que le niveau 3 vaut le coup, ou c\u2019est juste un produit d\u2019appel ? \u00bb Apr\u00e8s avoir adapt\u00e9 ce mod\u00e8le sur plusieurs patients, ma r\u00e9ponse est claire : c\u2019est un vrai appareil, pas un sous-produit. Mais il faut savoir \u00e0 quoi s\u2019attendre.\n\nCe que fait cet appareil\nLe Pure Charge&Go IX 3 partage la m\u00eame puce IX Platform que le niveau 7, avec la technologie OVP 2.0 qui traite votre propre voix s\u00e9par\u00e9ment. C\u2019est le m\u00eame moteur, mais avec moins de \u00ab r\u00e9solutions \u00bb dans le r\u00e9glage : 24 canaux et 12 bandes au lieu de 48 et 20 sur le niveau 7. En pratique, ce que \u00e7a change pour vous, c\u2019est surtout la finesse d\u2019adaptation dans les situations complexes. Dans le calme \u2014 conversations \u00e0 deux, t\u00e9l\u00e9vision, t\u00e9l\u00e9phone \u2014 la diff\u00e9rence avec le 7 est \u00e0 peine perceptible. Votre audioproth\u00e9siste r\u00e8gle l\u2019appareil, vous entendez mieux, point.\n\nL\u00e0 o\u00f9 l\u2019\u00e9cart se creuse, c\u2019est dans le bruit. Le niveau 3 dispose de moins d\u2019algorithmes automatiques pour g\u00e9rer les environnements multiples. Un d\u00eener en famille \u00e0 six ? Le 3 vous aidera, mais il faudra fournir un peu plus d\u2019effort de concentration qu\u2019avec un niveau 5 ou 7. Ce n\u2019est pas un d\u00e9faut de l\u2019appareil \u2014 c\u2019est la contrepartie du prix.\n\nLa gestion du larsen est identique \u00e0 celle du niveau 7 : exemplaire. C\u2019est un avantage de la puce IX, le syst\u00e8me anti-feedback n\u2019est pas brid\u00e9 selon les niveaux. Et l\u2019autonomie reste la m\u00eame : 34 \u00e0 39h selon votre utilisation du streaming.\n\nEn pratique, sur le terrain\nUn patient de 65 ans, premier appareillage, perte l\u00e9g\u00e8re bilat\u00e9rale. Il ne voulait pas investir 3 000\u20ac pour une paire sans savoir s\u2019il s\u2019adapterait. Le Pure IX 3 \u00e9tait le bon compromis \u2014 il b\u00e9n\u00e9ficie de la technologie IX sans le budget maximum. Apr\u00e8s deux mois d\u2019utilisation, il m\u2019a confirm\u00e9 que le confort dans le calme \u00e9tait excellent. Au restaurant, c\u2019\u00e9tait \u00ab mieux mais pas parfait \u00bb \u2014 ce qui est honn\u00eate pour un niveau d\u2019entr\u00e9e de gamme. Il a d\u00e9cid\u00e9 de garder ses appareils.\n\nUn d\u00e9tail pratique : le chargeur et les accessoires sont les m\u00eames que pour le niveau 7. Si vous montez en gamme plus tard, vous gardez tout l\u2019\u00e9cosyst\u00e8me. Et si vous utilisez d\u00e9j\u00e0 l\u2019application Signia App, elle fonctionne de la m\u00eame mani\u00e8re quel que soit le niveau.\n\nPour qui est fait cet appareil ?\nLe Pure IX 3 est particuli\u00e8rement adapt\u00e9 si vous \u00eates en premier appareillage avec une perte l\u00e9g\u00e8re \u00e0 mod\u00e9r\u00e9e, si votre quotidien est plut\u00f4t calme (maison, promenades, conversations \u00e0 deux), ou si votre budget ne permet pas le niveau 5 ou 7. C\u2019est aussi un choix pertinent pour les personnes qui ne savent pas encore si elles vont s\u2019adapter \u00e0 un appareillage \u2014 mieux vaut commencer avec un bon appareil \u00e0 prix accessible que retarder ind\u00e9finiment.\n\nSi votre vie sociale est active avec des d\u00eeners en groupe r\u00e9guliers, des r\u00e9unions ou des conf\u00e9rences, le niveau 5 ou 7 vous apportera un confort suppl\u00e9mentaire dans ces situations.\n\nPar rapport \u00e0 la concurrence\nPar rapport au Pure AX 3 (g\u00e9n\u00e9ration pr\u00e9c\u00e9dente), le gain principal est le traitement OVP 2.0 am\u00e9lior\u00e9 et la connectivit\u00e9 LE Audio. Face au niveau 5 (+200 \u00e0 300\u20ac), la diff\u00e9rence se joue principalement sur le nombre de canaux et d\u2019algorithmes de gestion du bruit. Face au niveau 7 (+300 \u00e0 500\u20ac), l\u2019\u00e9cart est plus marqu\u00e9 en situations bruyantes.\n\nCompare \u00e0 un Phonak Audeo Infinio 30 ou un Oticon Intent 1 dans la m\u00eame gamme de prix, le Pure IX 3 se distingue par sa gestion du larsen et le naturel de la propre voix. C\u2019est un choix qui se d\u00e9fend tr\u00e8s bien dans cette cat\u00e9gorie.\n\nVerdict expert\n7.8/10. Le Signia Pure Charge&Go IX 3 offre l\u2019essentiel de la technologie IX \u00e0 un prix accessible. Il ne triche pas sur la qualit\u00e9 de base \u2014 m\u00eame puce, m\u00eame anti-larsen, m\u00eame autonomie que le niveau 7. La contrepartie est une gestion du bruit moins fine dans les environnements complexes. Pour un premier appareillage ou un budget ma\u00eetris\u00e9, c\u2019est un excellent point d\u2019entr\u00e9e.\n\nEn une phrase : toute la fiabilit\u00e9 Signia IX \u00e0 moins de 1 100\u20ac, sans compromis sur l\u2019essentiel.",
  "pointsForts": [
    "M\u00eame puce IX Platform que le niveau 7 \u2014 OVP 2.0, anti-larsen et autonomie identiques",
    "Prix d\u2019entr\u00e9e dans la gamme IX : de 995 \u00e0 1 090\u20ac par appareil",
    "Autonomie g\u00e9n\u00e9reuse : 34 \u00e0 39h, chargeur et accessoires identiques au niveau 7",
    "Clart\u00e9 vocale tr\u00e8s satisfaisante dans le calme et les conversations \u00e0 deux",
    "Application Signia App compl\u00e8te et \u00e9volutive, compatible tous niveaux IX"
  ],
  "pointsFaibles": [
    "24 canaux au lieu de 48 \u2014 moins de finesse de r\u00e9glage dans les situations bruyantes complexes",
    "Pas de bobine T sur ce mod\u00e8le \u2014 la version Pure T IX existe si vous en avez besoin",
    "Algorithmes de gestion du bruit moins nombreux que sur les niveaux 5 et 7 \u2014 effort de concentration suppl\u00e9mentaire en milieu bruyant"
  ],
  "noteExpert": 7.8,
  "enAvant": false,
  "legacy": false,
  "metaTitle": "Signia Pure Charge&Go 3 IX : prix, avis et fiche",
  "metaDescription": "RIC Signia, puce IX, 24 canaux. Entr\u00e9e de gamme fiable et discr\u00e8te. De 995 \u00e0 1 090\u20ac par appareil. Avis d\u2019audioproth\u00e9siste DE."
}
