{
  "marque": "starkey",
  "marqueLabel": "Starkey",
  "groupe": "starkey",
  "modele": "Omega AI",
  "formeType": "RIC",
  "formesDisponibles": "mRIC R|RIC RT|RIC 312|ITE R|ITC R|CIC",
  "puce": "G3 Neuro",
  "annee": 2025,
  "specs": {
    "canaux": 64,
    "bandes": 24,
    "batterie": "Li-ion|312",
    "autonomie": "51",
    "ip": "IP68+",
    "reductionBruit": 22,
    "plageAdaptation": "Mild to severe"
  },
  "connectivite": {
    "bluetooth": "BLE LE Audio",
    "auracast": false,
    "application": "My Starkey",
    "mainLibre": true
  },
  "fonctionnalites": {
    "rechargeable": true,
    "bobineT": true,
    "acouphenes": true,
    "antiFeedback": "Yes (top)",
    "micDirectionnels": "DNN 360",
    "capteursSante": "Accel|Gyro|Fall|Resp"
  },
  "sourceUrl": "HearingTracker",
  "venduEnEurope": true,
  "slug": "starkey-omega-ai-16",
  "niveau": "16",
  "niveauRaw": "16",
  "niveauPosition": 1,
  "rac0": false,
  "prix": {
    "usd": {
      "min": 3398
    }
  },
  "image": "/images/appareils/aide-auditive-starkey-omega-ai-16.jpg",
  "descriptionCourte": "Le Starkey Omega AI 16 est un appareil auditif RIC entree de gamme equipe de la puce G3 Neuro, lance en 2025 par Starkey (groupe Starkey). Rechargeable avec 51h d'autonomie. Connectivite BLE LE Audio.",
  "pointsForts": [
    "Discret, leger, son naturel grace a l'ecouteur dans le conduit",
    "Puce G3 Neuro",
    "Rechargeable (51h)",
    "Bluetooth BLE LE Audio",
    "Etanche IP68+",
    "Generateur de bruit pour acouphenes"
  ],
  "pointsFaibles": [
    "Ecouteur expose au cerumen, necessitant un entretien regulier",
    "Pas de support Auracast",
    "Fonctionnalites reduites par rapport aux niveaux superieurs"
  ],
  "noteExpert": 7,
  "enAvant": false,
  "ficheTechniquePdf": "/docs/fiches-techniques/starkey-omega-ai-fiche-technique.pdf",
  "descriptionComplete": "Le Starkey Omega AI 16 est une aide auditive de type contour a ecouteur deporte (RIC), le format le plus repandu pour sa discretion et sa qualite sonore. Lance en 2025 par Starkey (groupe Starkey), leader en capteurs de sante integres, cet appareil se positionne en entree de gamme, avec les fonctionnalites essentielles pour une premiere adaptation.\n\nTechnologie et traitement du son\nEquipe de la puce G3 Neuro, le Omega AI beneficie de la technologie Neuro Processor avec Edge AI. Detection de chute, podometre, frequence cardiaque, traduction en temps reel. Le traitement du signal s'effectue sur 64 canaux et 24 bandes, permettant un ajustement fin de l'amplification par frequence. La plage d'adaptation couvre les pertes legeres a severes. \n\nConnectivite\nLa connectivite BLE LE Audio permet le streaming audio direct depuis votre smartphone. Les appels telephoniques se passent en mains libres, directement dans les appareils. L'application My Starkey permet de regler le volume, changer de programme et personnaliser l'ecoute depuis votre telephone. \n\nConfort et autonomie\nLe Omega AI est rechargeable (batterie Li-ion|312), offrant jusqu'a 51 heures d'autonomie par charge. Un chargeur est fourni avec l'appareil. La certification IP68+ garantit une resistance a l'eau et a la poussiere pour une utilisation sans souci au quotidien. \n\nFonctionnalites complementaires\nLe Omega AI integre egalement un generateur de bruit pour le soulagement des acouphenes, une bobine telephonique (T-coil) pour les boucles magnetiques, un systeme anti-larsen Yes (top), des microphones directionnels DNN 360, des capteurs de sante integres (Accel|Gyro|Fall|Resp). \n\nPrix et remboursement\nLe prix est communique sur devis par votre audioprothesiste. Un essai gratuit de 30 jours est obligatoire avant tout achat definitif.\n\nL'avis de l'audioprothesiste\nNote expert : 7/10. Le Starkey Omega AI 16 est un appareil auditif RIC entree de gamme equipe de la puce G3 Neuro, lance en 2025 par Starkey (groupe Starkey). Rechargeable avec 51h d'autonomie. Connectivite BLE LE Audio."
}
